picca/__init__.py
picca/_version.py
picca/cf.py
picca/co.py
picca/constants.py
picca/converters.py
picca/data.py
picca/io.py
picca/prep_del.py
picca/raw_io.py
picca/utils.py
picca/wedgize.py
picca/xcf.py
picca/bin/__init__.py
picca/bin/picca_Pk1D.py
picca/bin/picca_Pk1D_average_mean.py
picca/bin/picca_Pk1D_cross_exposure.py
picca/bin/picca_Pk1D_postprocess.py
picca/bin/picca_cf.py
picca/bin/picca_cf1d.py
picca/bin/picca_cf_angl.py
picca/bin/picca_co.py
picca/bin/picca_coadd_zint.py
picca/bin/picca_compute_fvoigt.py
picca/bin/picca_compute_fvoigt_hcd.py
picca/bin/picca_compute_pk_pksb.py
picca/bin/picca_convert_transmission.py
picca/bin/picca_delta_extraction.py
picca/bin/picca_dmat.py
picca/bin/picca_export.py
picca/bin/picca_export_co.py
picca/bin/picca_export_cross_covariance.py
picca/bin/picca_fast_metal_dmat.py
picca/bin/picca_fast_metal_xdmat.py
picca/bin/picca_metal_dmat.py
picca/bin/picca_metal_xdmat.py
picca/bin/picca_nersc_submit.py
picca/bin/picca_pk2fits.py
picca/bin/picca_reduce_spall.py
picca/bin/picca_wick.py
picca/bin/picca_xcf.py
picca/bin/picca_xcf1d.py
picca/bin/picca_xcf_angl.py
picca/bin/picca_xdmat.py
picca/bin/picca_xwick.py
picca/delta_extraction/__init__.py
picca/delta_extraction/astronomical_object.py
picca/delta_extraction/config.py
picca/delta_extraction/correction.py
picca/delta_extraction/data.py
picca/delta_extraction/errors.py
picca/delta_extraction/expected_flux.py
picca/delta_extraction/mask.py
picca/delta_extraction/quasar_catalogue.py
picca/delta_extraction/rejection_log.py
picca/delta_extraction/survey.py
picca/delta_extraction/utils.py
picca/delta_extraction/utils_pk1d.py
picca/delta_extraction/astronomical_objects/__init__.py
picca/delta_extraction/astronomical_objects/desi_forest.py
picca/delta_extraction/astronomical_objects/desi_pk1d_forest.py
picca/delta_extraction/astronomical_objects/forest.py
picca/delta_extraction/astronomical_objects/pk1d_forest.py
picca/delta_extraction/astronomical_objects/sdss_forest.py
picca-9.16.0.dist-info/licenses/LICENSE
picca-9.16.0.dist-info/METADATA
picca-9.16.0.dist-info/WHEEL
picca-9.16.0.dist-info/entry_points.txt
picca-9.16.0.dist-info/top_level.txt
picca-9.16.0.dist-info/RECORD
