Metadata-Version: 2.4
Name: picca
Version: 9.16.0
Summary: Package for Igm Cosmological-Correlations Analyses
Author: Nicolas Busca, Helion du Mas des Bourboux, Michael Walther, The DESI Lya forest picca topical group
Author-email: Ignasi Pérez-Ràfols <iprafols@gmail.com>
License-Expression: GPL-3.0-or-later
Project-URL: Homepage, https://github.com/igmhub/picca
Keywords: cosmology,lyman-alpha,bao
Classifier: Programming Language :: Python :: 3
Requires-Python: >=3.10
License-File: LICENSE
Requires-Dist: numpy>=2.0.0
Requires-Dist: scipy>=1.14.0
Requires-Dist: iminuit>=2.26.0
Requires-Dist: healpy>=1.17.1
Requires-Dist: fitsio>=1.2.4
Requires-Dist: llvmlite>=0.43.0
Requires-Dist: numba>=0.60.0
Requires-Dist: h5py>=3.11.0
Requires-Dist: future>=1.0.0
Requires-Dist: setuptools>=69.5.1
Requires-Dist: gitpython>=3.1.43
Dynamic: license-file
